superexpressive.py
super_expressive_python-0.0.2.dist-info/LICENSE
super_expressive_python-0.0.2.dist-info/METADATA
super_expressive_python-0.0.2.dist-info/WHEEL
super_expressive_python-0.0.2.dist-info/top_level.txt
super_expressive_python-0.0.2.dist-info/RECORD
