Metadata-Version: 2.1
Name: super-expressive-python
Version: 0.0.2
Summary: python port of super-expressive
Home-page: https://github.com/natedileas/super-expressive-python
Author: Nathan Dileas
Author-email: ndileas+super-expressive-python@gmail.com
License: UNKNOWN
Platform: UNKNOWN
